meine/__init__.py
meine/__main__.py
meine/app.py
meine/exceptions.py
meine/logger_config.py
meine/themes.py
meine/ui_handler.py
meine/Actions/Myrequest.py
meine/Actions/__init__.py
meine/Actions/app_theme.py
meine/Actions/file.py
meine/Actions/other.py
meine/Actions/system.py
meine/resources/customs.json
meine/resources/history.json
meine/resources/quotes.json
meine/resources/settings.json
meine/screens/__init__.py
meine/screens/help.py
meine/screens/home.py
meine/screens/me.py
meine/screens/settings.py
meine/screens/system_utils.py
meine/screens/textarea.py
meine/tcss/app.tcss
meine/tcss/help.tcss
meine/tcss/me.tcss
meine/tcss/setting.tcss
meine/utils/__init__.py
meine/utils/file_manager.py
meine/widgets/__init__.py
meine/widgets/containers.py
meine/widgets/directory_tree.py
meine/widgets/input.py
meine/widgets/system_widget_provider.py
meine-2.0.3.dist-info/licenses/LICENSE
meine-2.0.3.dist-info/METADATA
meine-2.0.3.dist-info/WHEEL
meine-2.0.3.dist-info/entry_points.txt
meine-2.0.3.dist-info/top_level.txt
meine-2.0.3.dist-info/RECORD
