Metadata-Version: 2.4
Name: meine
Version: 2.0.3
Summary: ⚡MeineRe - A regex-powered, asynchronous CLI file manager and system utility built with Textual. It combines intuitive command parsing with rich terminal UI, allowing you to navigate directories, manage files, and fetch system info—fast.
Author-email: balaji j <j.balaji2468@gmail.com>
Project-URL: Homepage, https://github.com/Balaji01-4D/meine
Project-URL: Bug Tracker, https://github.com/Balaji01-4D/meine/issues
Project-URL: License, https://github.com/Balaji01-4D/meine/blob/main/LICENSE
Keywords: cli,file-manager,textual,regex,terminal-ui,system-utility
Classifier: Programming Language :: Python :: 3
Classifier: License :: OSI Approved :: MIT License
Classifier: Operating System :: OS Independent
Requires-Python: >=3.11
License-File: LICENSE
Requires-Dist: aiofiles<25.0.0,>=24.1.0
Requires-Dist: appdirs<2.0.0,>=1.4.4
Requires-Dist: click<9.0.0,>=8.2.1
Requires-Dist: linkify-it-py<3.0.0,>=2.0.3
Requires-Dist: markdown-it-py<4.0.0,>=3.0.0
Requires-Dist: mdit-py-plugins<0.5.0,>=0.4.2
Requires-Dist: mdurl<0.2.0,>=0.1.2
Requires-Dist: multivolumefile<0.3.0,>=0.2.3
Requires-Dist: platformdirs<5.0.0,>=4.3.8
Requires-Dist: psutil<8.0.0,>=7.0.0
Requires-Dist: rich<15.0.0,>=14.0.0
Requires-Dist: textual<7.1.1,>=6.6.0
Requires-Dist: typing_extensions<5.0.0,>=4.13.2
Requires-Dist: uc-micro-py<2.0.0,>=1.0.3
Dynamic: license-file
